chatgpt_pre_commit_hooks/__init__.py
chatgpt_pre_commit_hooks/base.py
chatgpt_pre_commit_hooks/hook_chatgpt_commit_message.py
chatgpt_pre_commit_hooks/logger.py
chatgpt_pre_commit_hooks/main.py
chatgpt_pre_commit_hooks/utils.py
chatgpt_pre_commit_hooks-0.1.3.dist-info/LICENSE
chatgpt_pre_commit_hooks-0.1.3.dist-info/METADATA
chatgpt_pre_commit_hooks-0.1.3.dist-info/WHEEL
chatgpt_pre_commit_hooks-0.1.3.dist-info/entry_points.txt
chatgpt_pre_commit_hooks-0.1.3.dist-info/top_level.txt
chatgpt_pre_commit_hooks-0.1.3.dist-info/RECORD
