Metadata-Version: 2.1
Name: chatgpt-pre-commit-hooks
Version: 0.1.3
Summary: Pre-commit hooks collection that utilizes ChatGPT and OpenAI platform to validate modifications made to the codebase.
Author-email: Dariusz Porowski <3431813+dariuszporowski@users.noreply.github.com>
License: MIT
Project-URL: Homepage, https://github.com/DariuszPorowski/chatgpt-pre-commit-hooks/blob/main/README.md
Project-URL: Bug Tracker, https://github.com/DariuszPorowski/chatgpt-pre-commit-hooks/issues
Keywords: chatgpt,openai,pre-commit,pre-commit-hooks,pre-commit-hook
Classifier: Development Status :: 3 - Alpha
Classifier: Intended Audience :: Developers
Classifier: Intended Audience :: Information Technology
Classifier: License :: OSI Approved :: MIT License
Classifier: Operating System :: OS Independent
Classifier: Programming Language :: Python
Classifier: Programming Language :: Python :: 3
Classifier: Programming Language :: Python :: 3 :: Only
Classifier: Topic :: Scientific/Engineering :: Artificial Intelligence
Classifier: Topic :: Software Development :: Version Control
Classifier: Topic :: Software Development :: Version Control :: Git
Requires-Python: >=3.8
License-File: LICENSE
Requires-Dist: openai (~=0.27.4)
Requires-Dist: tiktoken (~=0.3.3)
Provides-Extra: build
Requires-Dist: build ; extra == 'build'
Requires-Dist: wheel ; extra == 'build'
Requires-Dist: twine ; extra == 'build'
Provides-Extra: dev
Requires-Dist: ruff ; extra == 'dev'
Requires-Dist: mypy ; extra == 'dev'
Requires-Dist: pre-commit ; extra == 'dev'
Requires-Dist: pyyaml ; extra == 'dev'
Requires-Dist: types-PyYAML ; extra == 'dev'
